apipulse_python/__init__.py
apipulse_python/sdk_logger.py
apipulse_python/sdk_version.py
apipulse_python/api_pulse_middleware/__init__.py
apipulse_python/api_pulse_middleware/collect_urls.py
apipulse_python/api_pulse_middleware/constants.py
apipulse_python/api_pulse_middleware/contract.py
apipulse_python/api_pulse_middleware/middleware.py
apipulse_python/api_pulse_middleware/utils.py
apipulse_python/apipulse_sdk.egg-info/PKG-INFO
apipulse_python/apipulse_sdk.egg-info/SOURCES.txt
apipulse_python/apipulse_sdk.egg-info/dependency_links.txt
apipulse_python/apipulse_sdk.egg-info/requires.txt
apipulse_python/apipulse_sdk.egg-info/top_level.txt
apipulse_python/core/__init__.py
apipulse_python/core/always_capture_sync.py
apipulse_python/core/api_processor.py
apipulse_python/core/apipulse_sdk.py
apipulse_python/core/auto_configuration.py
apipulse_python/core/scheduled_timer.py
apipulse_python/core/buffer/abstract_buffer_manager.py
apipulse_python/core/buffer/api_buffer_key.py
apipulse_python/core/buffer/buffer.py
apipulse_python/core/buffer/buffer_manager_worker.py
apipulse_python/core/buffer/discovered_buffer_manager.py
apipulse_python/core/buffer/no_op_buffer_manager.py
apipulse_python/core/buffer/registered_buffer_manager.py
apipulse_python/core/buffer/simple_buffer.py
apipulse_python/core/config/config_manager.py
apipulse_python/core/config/config_update_listener.py
apipulse_python/core/config/config_validators.py
apipulse_python/core/config/simple_config_manager.py
apipulse_python/core/constant/__init__.py
apipulse_python/core/constant/http_method.py
apipulse_python/core/constant/segment_template_type.py
apipulse_python/core/filter/__init__.py
apipulse_python/core/filter/always_capture_filter.py
apipulse_python/core/filter/filter.py
apipulse_python/core/http/__init__.py
apipulse_python/core/http/context.py
apipulse_python/core/http/http_connection.py
apipulse_python/core/http/http_request.py
apipulse_python/core/http/http_response.py
apipulse_python/core/model/__init__.py
apipulse_python/core/model/agent_config.py
apipulse_python/core/model/api_config.py
apipulse_python/core/model/api_sample.py
apipulse_python/core/model/black_list_rule.py
apipulse_python/core/model/observed_api.py
apipulse_python/core/model/sdk_options.py
apipulse_sdk-0.1.3.dist-info/METADATA
apipulse_sdk-0.1.3.dist-info/WHEEL
apipulse_sdk-0.1.3.dist-info/top_level.txt
apipulse_sdk-0.1.3.dist-info/RECORD
