Metadata-Version: 2.1
Name: apipulse-sdk
Version: 0.1.3
Summary: Api automation testing sdk for django framework
Home-page: http://github.com/yourusername/your-middleware
Author: Vikram Panwar
Author-email: vikram.panwar@apipulse.dev
License: unlicensed
Classifier: Framework :: Django
Classifier: Intended Audience :: Developers
Classifier: License :: Other/Proprietary License
Requires-Dist: Django >=3.0
Requires-Dist: requests
Requires-Dist: pydantic
